[
  {
    "id": 1,
    "slug": "rodrigo-hdez",
    "nombre": "Irving Rodrigo",
    "apellidos": "Hernández Tesillos",
    "cv": "/documentos/cv_rodrigo.pdf",
    "puesto": "Supervisor de Procesos",
    "area": "Equipo de Datos",
    "foto": "https://ui-avatars.com/api/?name=Rodrigo+Hernandez&background=9D2449&color=fff",
    "telefono": "55-4547-6654",
    "correo": "irving.hernandez@imssbienestar.gob.mx",
    "link_mapa": "https://maps.app.goo.gl/GoVtqX5uj4LJmfpb7",
    "ubicacion": "Av. Insurgentes Centro 1940, Florida, Álvaro Obregón, 01020 Ciudad de México, CDMX, Piso 3"
  },

  
  {
    "id": 2,
    "slug": "ned-romero",
    "nombre": "Dr. Ned I.",
    "apellidos": "Romero Morales",
    "cv": "/documentos/cv_rodrigo.pdf",
    "puesto": "Titular de la Division de Hospitales",
    "area": "Coordinación Unidades Segundo Nivel",
    "foto": "https://ui-avatars.com/api/?name=Ned+Romero&background=9D2449&color=fff",
    "telefono": "55-5438-6861",
    "correo": "ned.romero@imssbienestar.gob.mx",
    "link_mapa": "https://maps.app.goo.gl/GoVtqX5uj4LJmfpb7",
    "ubicacion": "Av. Insurgentes Centro 1940, Florida, Álvaro Obregón, 01020 Ciudad de México, CDMX, Piso 3"
  }
]